Metadata-Version: 2.1
Name: DeepARG
Version: 1.0.2
Summary: UNKNOWN
Home-page: UNKNOWN
License: UNKNOWN
Platform: UNKNOWN
Requires-Python: >=2.7.15,!=3.*
Requires-Dist: numpy (==1.10.4)
Requires-Dist: scipy (==0.16.1)
Requires-Dist: joblib (==0.13.0)
Requires-Dist: BioPython (==1.73)
Requires-Dist: ete3
Requires-Dist: tqdm
Requires-Dist: nolearn (==0.6)
Requires-Dist: lasagne (==0.1)
Requires-Dist: scikit-learn (==0.19.1)
Requires-Dist: theano (==0.8.2)
Requires-Dist: requests (==2.18.4)
Requires-Dist: wget
